{"url": "http://www.youtube.com/watch?v=V1YFdGQqJdE&feature=player_embedded", "text": "", "images": ["https://www.youtube.com/s/desktop/3c5cb7b3/img/favicon.ico"], "top_img": "https://www.youtube.com/s/desktop/3c5cb7b3/img/favicon.ico", "keywords": [], "authors": [], "canonical_link": "http://www.youtube.com/undefined", "title": "- YouTube", "meta_data": {"theme-color": "rgba(255, 255, 255, 0.98)", "description": "\u5728 YouTube \u4e0a\u76e1\u60c5\u4eab\u53d7\u81ea\u5df1\u559c\u611b\u7684\u5f71\u7247\u548c\u97f3\u6a02\u3001\u4e0a\u50b3\u539f\u5275\u5167\u5bb9\uff0c\u4e26\u8207\u89aa\u670b\u597d\u53cb\u548c\u5168\u4e16\u754c\u89c0\u773e\u5206\u4eab\u4f60\u7684\u5f71\u7247\u3002", "keywords": "\u5f71\u7247, \u5206\u4eab, \u53ef\u62cd\u7167\u7684\u624b\u6a5f, \u5f71\u50cf\u96fb\u8a71, \u514d\u8cbb, \u4e0a\u50b3"}, "movies": [], "publish_date": null, "source": "http://www.youtube.com", "summary": ""}